MoSort/__init__.py
MoSort/bubble_sort.py
MoSort/heap_sort.py
MoSort/insertion_sort.py
MoSort/merge_sort.py
MoSort/quick_sort.py
MoSort/selection_sort.py
MoSort/tim_sort.py
tests/__init__.py
tests/test_sorts.py
MoSort-0.1.5.dist-info/LICENSE
MoSort-0.1.5.dist-info/METADATA
MoSort-0.1.5.dist-info/WHEEL
MoSort-0.1.5.dist-info/top_level.txt
MoSort-0.1.5.dist-info/RECORD
