Metadata-Version: 2.1
Name: MoSort
Version: 0.1.5
Summary: A Python library that provides various sorting algorithms including Bubble Sort, Quick Sort, Merge Sort, Insertion Sort, Selection Sort,Tim Sort, and Heap Sort. Written by Mohammad E. Eslami.
Home-page: https://github.com/Mohammades/
Author: Mohammad.E Eslami
Author-email: mohamad.slami@gmail.com
Classifier: Programming Language :: Python :: 3
Classifier: License :: OSI Approved :: MIT License
Classifier: Operating System :: OS Independent
Requires-Python: >=3.6
License-File: LICENSE
